{"flights": [{"flight_number": "CZ8490", "type": "Departure", "departure_time": "2024-09-17 03:55:00", "airline_name": "China Southern Airlines", "destination": "Guangzhou (CAN)", "terminal": "T1", "gate_number": "C19"}, {"flight_number": "6E1016", "type": "Departure", "departure_time": "2024-09-17 04:15:00", "airline_name": "IndiGo", "destination": "Kolkata (CCU)", "terminal": "T2", "gate_number": "F35"}, {"flight_number": "TR456", "type": "Departure", "departure_time": "2024-09-17 04:50:00", "airline_name": "Scoot", "destination": "Kuala Lumpur (KUL)", "terminal": "T1", "gate_number": "D30"}, {"flight_number": "6E1008", "type": "Departure", "departure_time": "2024-09-17 04:55:00", "airline_name": "IndiGo", "destination": "Tiruchirappalli (TRZ)", "terminal": "T2", "gate_number": "F35"}, {"flight_number": "TR100", "type": "Departure", "departure_time": "2024-09-17 05:15:00", "airline_name": "Scoot", "destination": "Guangzhou (CAN)", "terminal": "T1", "gate_number": "D37"}, {"flight_number": "TR410", "type": "Departure", "departure_time": "2024-09-17 05:25:00", "airline_name": "Scoot", "destination": "Sibu (SBW)", "terminal": "T1", "gate_number": "D43"}, {"flight_number": "6E1006", "type": "Departure", "departure_time": "2024-09-17 05:30:00", "airline_name": "IndiGo", "destination": "Bengaluru (BLR)", "terminal": "T2", "gate_number": "F52"}, {"flight_number": "BS308", "type": "Departure", "departure_time": "2024-09-17 05:40:00", "airline_name": "US-Bangla Airlines", "destination": "Dhaka (DAC)", "terminal": "T3", "gate_number": "A9"}, {"flight_number": "3K761", "type": "Departure", "departure_time": "2024-09-17 06:00:00", "airline_name": "Jetstar Asia", "destination": "Manila (MNL)", "terminal": "T4", "gate_number": "G10"}, {"flight_number": "6E1018", "type": "Departure", "departure_time": "2024-09-17 06:00:00", "airline_name": "IndiGo", "destination": "Bhubaneswar (BBI)", "terminal": "T2", "gate_number": "F50"}, {"flight_number": "NH802", "type": "Departure", "departure_time": "2024-09-17 06:15:00", "airline_name": "All Nippon Airways", "destination": "Tokyo (Narita) (NRT)", "terminal": "T2", "gate_number": "E11"}, {"flight_number": "MH602", "type": "Departure", "departure_time": "2024-09-17 06:20:00", "airline_name": "Malaysia Airlines", "destination": "Kuala Lumpur (KUL)", "terminal": "T2", "gate_number": "E7"}, {"flight_number": "SQ950", "type": "Departure", "departure_time": "2024-09-17 06:20:00", "airline_name": "Singapore Airlines", "destination": "Jakarta (CGK)", "terminal": "T2", "gate_number": "E26"}, {"flight_number": "CX692", "type": "Departure", "departure_time": "2024-09-17 06:30:00", "airline_name": "Cathay Pacific", "destination": "Hong Kong (HKG)", "terminal": "T4", "gate_number": "G18"}, {"flight_number": "TR818", "type": "Departure", "departure_time": "2024-09-17 06:35:00", "airline_name": "Scoot", "destination": "Osaka (KIX)", "terminal": "T1", "gate_number": "D32"}, {"flight_number": "SQ934", "type": "Departure", "departure_time": "2024-09-17 06:45:00", "airline_name": "Singapore Airlines", "destination": "Bali-Denpasar (DPS)", "terminal": "T2", "gate_number": "F60"}, {"flight_number": "TR488", "type": "Departure", "departure_time": "2024-09-17 06:45:00", "airline_name": "Scoot", "destination": "Ipoh (IPH)", "terminal": "T1", "gate_number": "C18"}, {"flight_number": "JQ96", "type": "Departure", "departure_time": "2024-09-17 06:55:00", "airline_name": "Jetstar International", "destination": "Perth (PER)", "terminal": "T4", "gate_number": "G17"}, {"flight_number": "3K683", "type": "Departure", "departure_time": "2024-09-17 07:00:00", "airline_name": "Jetstar Asia", "destination": "Kuala Lumpur (KUL)", "terminal": "T4", "gate_number": "G1"}, {"flight_number": "TR304", "type": "Departure", "departure_time": "2024-09-17 07:00:00", "airline_name": "Scoot", "destination": "Ho Chi Minh City (SGN)", "terminal": "T1", "gate_number": "D33"}, {"flight_number": "TR640", "type": "Departure", "departure_time": "2024-09-17 07:00:00", "airline_name": "Scoot", "destination": "Koh Samui (USM)", "terminal": "T1", "gate_number": "D43"}, {"flight_number": "SQ104", "type": "Departure", "departure_time": "2024-09-17 07:05:00", "airline_name": "Singapore Airlines", "destination": "Kuala Lumpur (KUL)", "terminal": "T2", "gate_number": "E6"}, {"flight_number": "TR978", "type": "Departure", "departure_time": "2024-09-17 07:05:00", "airline_name": "Scoot", "destination": "Hong Kong (HKG)", "terminal": "T1", "gate_number": "D36"}, {"flight_number": "SQ706", "type": "Departure", "departure_time": "2024-09-17 07:10:00", "airline_name": "Singapore Airlines", "destination": "Bangkok (Suvarnabhumi) (BKK)", "terminal": "T2", "gate_number": "F40"}, {"flight_number": "TR174", "type": "Departure", "departure_time": "2024-09-17 07:10:00", "airline_name": "Scoot", "destination": "Fuzhou (FOC)", "terminal": "T1", "gate_number": "C17"}, {"flight_number": "TR280", "type": "Departure", "departure_time": "2024-09-17 07:10:00", "airline_name": "Scoot", "destination": "Bali-Denpasar (DPS)", "terminal": "T1", "gate_number": "C13"}, {"flight_number": "3K511", "type": "Departure", "departure_time": "2024-09-17 07:15:00", "airline_name": "Jetstar Asia", "destination": "Bangkok (Suvarnabhumi) (BKK)", "terminal": "T4", "gate_number": "G11"}, {"flight_number": "SQ213", "type": "Departure", "departure_time": "2024-09-17 07:15:00", "airline_name": "Singapore Airlines", "destination": "Perth (PER)", "terminal": "T3", "gate_number": "B8"}, {"flight_number": "SQ241", "type": "Departure", "departure_time": "2024-09-17 07:15:00", "airline_name": "Singapore Airlines", "destination": "Sydney (SYD)", "terminal": "T3", "gate_number": "C22"}, {"flight_number": "3K573", "type": "Departure", "departure_time": "2024-09-17 07:20:00", "airline_name": "Jetstar Asia", "destination": "Krabi (KBV)", "terminal": "T4", "gate_number": "G7"}, {"flight_number": "3K671", "type": "Departure", "departure_time": "2024-09-17 07:25:00", "airline_name": "Jetstar Asia", "destination": "Penang (PEN)", "terminal": "T4", "gate_number": "G5"}, {"flight_number": "3K817", "type": "Departure", "departure_time": "2024-09-17 07:25:00", "airline_name": "Jetstar Asia", "destination": "Haikou (HAK)", "terminal": "T4", "gate_number": "G9"}, {"flight_number": "GA823", "type": "Departure", "departure_time": "2024-09-17 07:25:00", "airline_name": "Garuda Indonesia", "destination": "Jakarta (CGK)", "terminal": "T3", "gate_number": "C11"}, {"flight_number": "SQ874", "type": "Departure", "departure_time": "2024-09-17 07:25:00", "airline_name": "Singapore Airlines", "destination": "Hong Kong (HKG)", "terminal": "T3", "gate_number": "B1"}, {"flight_number": "TR658", "type": "Departure", "departure_time": "2024-09-17 07:25:00", "airline_name": "Scoot", "destination": "Phuket (HKT)", "terminal": "T1", "gate_number": "D38"}, {"flight_number": "SQ154", "type": "Departure", "departure_time": "2024-09-17 07:30:00", "airline_name": "Singapore Airlines", "destination": "Phnom Penh (PNH)", "terminal": "T2", "gate_number": "F52"}, {"flight_number": "SQ422", "type": "Departure", "departure_time": "2024-09-17 07:40:00", "airline_name": "Singapore Airlines", "destination": "Mumbai (BOM)", "terminal": "T3", "gate_number": "B2"}, {"flight_number": "SQ990", "type": "Departure", "departure_time": "2024-09-17 07:40:00", "airline_name": "Singapore Airlines", "destination": "Medan (KNO)", "terminal": "T2", "gate_number": "D42"}, {"flight_number": "AK700", "type": "Departure", "departure_time": "2024-09-17 07:45:00", "airline_name": "AirAsia", "destination": "Kuala Lumpur (KUL)", "terminal": "T4", "gate_number": "G2"}, {"flight_number": "TR258", "type": "Departure", "departure_time": "2024-09-17 07:45:00", "airline_name": "Scoot", "destination": "Lombok (LOP)", "terminal": "T1", "gate_number": "D47"}, {"flight_number": "3K201", "type": "Departure", "departure_time": "2024-09-17 07:50:00", "airline_name": "Jetstar Asia", "destination": "Jakarta (CGK)", "terminal": "T4", "gate_number": "G6"}, {"flight_number": "SQ207", "type": "Departure", "departure_time": "2024-09-17 07:50:00", "airline_name": "Singapore Airlines", "destination": "Melbourne (MEL)", "terminal": "T3", "gate_number": "A3"}, {"flight_number": "SQ868", "type": "Departure", "departure_time": "2024-09-17 07:50:00", "airline_name": "Singapore Airlines", "destination": "Xiamen (XMN)", "terminal": "T3", "gate_number": "A18"}, {"flight_number": "SQ922", "type": "Departure", "departure_time": "2024-09-17 07:50:00", "airline_name": "Singapore Airlines", "destination": "Surabaya (SUB)", "terminal": "T2", "gate_number": "D40"}, {"flight_number": "SQ762", "type": "Departure", "departure_time": "2024-09-17 07:55:00", "airline_name": "Singapore Airlines", "destination": "Yangon (RGN)", "terminal": "T2", "gate_number": "F35"}, {"flight_number": "SQ828", "type": "Departure", "departure_time": "2024-09-17 07:55:00", "airline_name": "Singapore Airlines", "destination": "Shanghai (PVG)", "terminal": "T3", "gate_number": "A16"}, {"flight_number": "TR222", "type": "Departure", "departure_time": "2024-09-17 07:55:00", "airline_name": "Scoot", "destination": "Balikpapan (BPN)", "terminal": "T1", "gate_number": "C12"}, {"flight_number": "CX710", "type": "Departure", "departure_time": "2024-09-17 08:00:00", "airline_name": "Cathay Pacific", "destination": "Hong Kong (HKG)", "terminal": "T4", "gate_number": "G20"}, {"flight_number": "CZ352", "type": "Departure", "departure_time": "2024-09-17 08:00:00", "airline_name": "China Southern Airlines", "destination": "Guangzhou (CAN)", "terminal": "T1", "gate_number": "D35"}, {"flight_number": "SQ132", "type": "Departure", "departure_time": "2024-09-17 08:00:00", "airline_name": "Singapore Airlines", "destination": "Penang (PEN)", "terminal": "T2", "gate_number": "F52"}, {"flight_number": "SQ600", "type": "Departure", "departure_time": "2024-09-17 08:00:00", "airline_name": "Singapore Airlines", "destination": "Seoul (ICN)", "terminal": "T2", "gate_number": "F59"}, {"flight_number": "SQ632", "type": "Departure", "departure_time": "2024-09-17 08:00:00", "airline_name": "Singapore Airlines", "destination": "Tokyo (Haneda) (HND)", "terminal": "T2", "gate_number": "E12"}, {"flight_number": "SQ850", "type": "Departure", "departure_time": "2024-09-17 08:00:00", "airline_name": "Singapore Airlines", "destination": "Guangzhou (CAN)", "terminal": "T3", "gate_number": "B7"}, {"flight_number": "JL712", "type": "Departure", "departure_time": "2024-09-17 08:05:00", "airline_name": "Japan Airlines", "destination": "Tokyo (Narita) (NRT)", "terminal": "T1", "gate_number": "D44"}, {"flight_number": "SQ726", "type": "Departure", "departure_time": "2024-09-17 08:05:00", "airline_name": "Singapore Airlines", "destination": "Phuket (HKT)", "terminal": "T2", "gate_number": "F36"}, {"flight_number": "TR262", "type": "Departure", "departure_time": "2024-09-17 08:05:00", "airline_name": "Scoot", "destination": "Surabaya (SUB)", "terminal": "T1", "gate_number": "D30"}, {"flight_number": "TR478", "type": "Departure", "departure_time": "2024-09-17 08:10:00", "airline_name": "Scoot", "destination": "Langkawi (LGK)", "terminal": "T1", "gate_number": "D37"}, {"flight_number": "CZ8490", "type": "Departure", "departure_time": "2024-09-18 03:55:00", "airline_name": "China Southern Airlines", "destination": "Guangzhou (CAN)", "terminal": "T1", "gate_number": "C19"}, {"flight_number": "CZ8490", "type": "Departure", "departure_time": "2024-09-19 03:55:00", "airline_name": "China Southern Airlines", "destination": "Guangzhou (CAN)", "terminal": "T1", "gate_number": "C19"}], "number_of_flights": 54}